dot_to_osscript/__init__.py
dot_to_osscript/__main__.py
dot_to_osscript/_read.py
dot_to_osscript/_write.py
dot_to_osscript/generate.py
dot_to_osscript-0.3.1.dist-info/LICENSE
dot_to_osscript-0.3.1.dist-info/METADATA
dot_to_osscript-0.3.1.dist-info/WHEEL
dot_to_osscript-0.3.1.dist-info/top_level.txt
dot_to_osscript-0.3.1.dist-info/RECORD
